pyenshash/__init__.py
pyenshash/utils.py
pyenshash-1.0.0.dist-info/METADATA
pyenshash-1.0.0.dist-info/WHEEL
pyenshash-1.0.0.dist-info/licenses/LICENSE
pyenshash-1.0.0.dist-info/RECORD
