Metadata-Version: 2.1
Name: pyenshash
Version: 1.0.0
Summary: Package containing basic functions related to Ethereum Name Service platform., such as namehash, labelhash, etc.
Project-URL: Homepage, https://github.com/szanuje/pyenshash
Project-URL: Bug Tracker, https://github.com/szanuje/pyenshash/issues
Author: szanuje
License: MIT License (MIT)
Classifier: License :: OSI Approved :: MIT License
Classifier: Operating System :: OS Independent
Classifier: Programming Language :: Python :: 3
Requires-Python: >=3.6
